{
  "scene_id": 1040,
  "frame_name": "frame_032454.jpg",
  "start_time": 16224.5,
  "end_time": 16228.5,
  "visual_analysis": {
    "layout": "",
    "elements": [],
    "extracted_formulas": [],
    "extracted_code": [],
    "extracted_diagrams": []
  },
  "text_analysis": {
    "key_concepts": [],
    "summary": "잠시만요. 요거는 제가 조금 헤매고 있는데. 어"
  },
  "integrated_analysis": {
    "visual_only_info": "",
    "text_only_info": "",
    "combined_insight": ""
  },
  "reference_needs": [],
  "is_important_frame": true,
  "importance_reason": "IN-02: 콘텐츠 프레임 (시각 정보 포함)",
  "importance_rule_version": 1
}