{
  "scene_id": 44,
  "frame_name": "frame_002257.jpg",
  "start_time": 1086.0,
  "end_time": 1170.0,
  "visual_analysis": {
    "layout": "",
    "elements": [],
    "extracted_formulas": [],
    "extracted_code": [],
    "extracted_diagrams": []
  },
  "text_analysis": {
    "key_concepts": [],
    "summary": "네, 소개를 드리도록 하겠습니다. 네, 아마 이거 보신 분들 많으실 겁니다. 저도 이제 라이브나 뉴스대를 항상 강조를 들었는데 네. 샘 알트만 오픈 AI의 채 GPT를 만든 오픈 AI CEO 샘 알트만이 이런 말을 남겼죠. 조만간 한 명이 운영하는 1조원 가치 기업이 나온다. 네. 빌리언 달러 컴퍼니 즉 그 유니콘 기업이 나온다라고 이렇게 그 언급을 한게 굉장히 화제가 많이 됐는데요. 네. 진짜로 이런 시대가 오고 있습니다. 아. 아, 되게 좋은 말씀 해 주셨는데. 네. 시작 전에 좋아요를 먼저 눌러야 됩니다. 아주 훌륭한 말씀입니다. 네. 좋아요 한 번씩만 꼭 부탁드리겠습니다. 네. 시작 전에 좋아요 한 번씩. 지금 좋아요 숫자가 네. 어이고. 어, 여기서는 왜 안 보이지? 어,이 유튜브 스튜디오가 좀 바뀐 거 같아요. 관리. 아, 이제 보인다. 네. 좋아요가 161개. 어, 719명이 계신데 아, 아직 좋아요는 161개밖에 안 됩니다. 한 번씩만 눌러 주시면 네, 감사드리겠습니다. 네, 좋습니다. 그러면 진행해 보겠습니다. 일단은 다들 아시겠지만 이제 그 1인 프로덕트 빌더의 시대가 왜 오고 있는가 이제 진행을 해 보도록 할 텐데요. 네. 세말트만이 남긴 유명한 말. AI로 인해서 조만간 한 명이 운영하는 1조원 기업이 나온다라고 이렇게 한게 화제가 됐고요. 실제로 그런 시대가 오고"
  },
  "integrated_analysis": {
    "visual_only_info": "",
    "text_only_info": "",
    "combined_insight": ""
  },
  "reference_needs": [],
  "is_important_frame": true,
  "importance_reason": "IN-01/02: 콘텐츠 프레임 + 지시대명사/시각키워드",
  "importance_rule_version": 1
}