{
  "scene_id": 962,
  "frame_name": "frame_030842.jpg",
  "start_time": 15416.5,
  "end_time": 15424.5,
  "visual_analysis": {
    "layout": "",
    "elements": [],
    "extracted_formulas": [],
    "extracted_code": [],
    "extracted_diagrams": []
  },
  "text_analysis": {
    "key_concepts": [],
    "summary": "프로필 눌러서 레포지토리 누르면 내가 쫙 작업한 작업들이 나오는데 프로덕 빌더 렉처가 이번에 제가 만든 거잖아요. 얘를 클릭하면"
  },
  "integrated_analysis": {
    "visual_only_info": "",
    "text_only_info": "",
    "combined_insight": ""
  },
  "reference_needs": [],
  "is_important_frame": true,
  "importance_reason": "IN-02: 콘텐츠 프레임 (시각 정보 포함)",
  "importance_rule_version": 1
}