{
  "scene_id": 810,
  "frame_name": "frame_027711.jpg",
  "start_time": 13851.0,
  "end_time": 13859.0,
  "visual_analysis": {
    "layout": "",
    "elements": [],
    "extracted_formulas": [],
    "extracted_code": [],
    "extracted_diagrams": []
  },
  "text_analysis": {
    "key_concepts": [],
    "summary": "입력하면 되니까 코덱스 엔터. 오, 네. 동굴동굴 돌아가면서 아, 이제 이렇게 나오죠. 이거 쭉"
  },
  "integrated_analysis": {
    "visual_only_info": "",
    "text_only_info": "",
    "combined_insight": ""
  },
  "reference_needs": [],
  "is_important_frame": true,
  "importance_reason": "IN-01/02: 콘텐츠 프레임 + 지시대명사/시각키워드",
  "importance_rule_version": 1
}